steer_opencell_design/__init__.py
steer_opencell_design/Components/Electrodes.py
steer_opencell_design/Components/Separators.py
steer_opencell_design/Components/__init__.py
steer_opencell_design/Components/Containers/Base.py
steer_opencell_design/Components/Containers/Cylindrical.py
steer_opencell_design/Components/Containers/Flexframe.py
steer_opencell_design/Components/Containers/Pouch.py
steer_opencell_design/Components/Containers/Prismatic.py
steer_opencell_design/Components/CurrentCollectors/Base.py
steer_opencell_design/Components/CurrentCollectors/Notched.py
steer_opencell_design/Components/CurrentCollectors/Punched.py
steer_opencell_design/Components/CurrentCollectors/Tabbed.py
steer_opencell_design/Components/CurrentCollectors/Tabless.py
steer_opencell_design/Components/CurrentCollectors/__init__.py
steer_opencell_design/Constructions/__init__.py
steer_opencell_design/Constructions/Cells/Base.py
steer_opencell_design/Constructions/Cells/CylindricalCell.py
steer_opencell_design/Constructions/Cells/FlexFrameCell.py
steer_opencell_design/Constructions/Cells/PouchCell.py
steer_opencell_design/Constructions/Cells/PrismaticCell.py
steer_opencell_design/Constructions/Cells/__init__.py
steer_opencell_design/Constructions/ElectrodeAssemblies/Base.py
steer_opencell_design/Constructions/ElectrodeAssemblies/JellyRolls.py
steer_opencell_design/Constructions/ElectrodeAssemblies/SpiralUtils.py
steer_opencell_design/Constructions/ElectrodeAssemblies/Stacks.py
steer_opencell_design/Constructions/ElectrodeAssemblies/Tape.py
steer_opencell_design/Constructions/ElectrodeAssemblies/WindingEquipment.py
steer_opencell_design/Constructions/ElectrodeAssemblies/__init__.py
steer_opencell_design/Constructions/Layups/ArealCapacityCurveUtils.py
steer_opencell_design/Constructions/Layups/Base.py
steer_opencell_design/Constructions/Layups/Laminate.py
steer_opencell_design/Constructions/Layups/MonoLayers.py
steer_opencell_design/Constructions/Layups/OverhangUtils.py
steer_opencell_design-1.0.13.dist-info/licenses/LICENCE.txt
steer_opencell_design-1.0.13.dist-info/METADATA
steer_opencell_design-1.0.13.dist-info/WHEEL
steer_opencell_design-1.0.13.dist-info/top_level.txt
steer_opencell_design-1.0.13.dist-info/RECORD
