Metadata-Version: 2.4
Name: steer-opencell-design
Version: 1.0.13
Summary: STEER OpenCell Design - A Python package for designing and modeling battery cells.
Author-email: Nicholas Siemons <nsiemons@stanford.edu>
License: MIT
Project-URL: Homepage, https://github.com/stanford-developers/steer-opencell-design/
Project-URL: Repository, https://github.com/stanford-developers/steer-opencell-design/
Classifier: Programming Language :: Python :: 3
Classifier: Operating System :: OS Independent
Requires-Python: >=3.10
License-File: LICENCE.txt
Requires-Dist: steer-core==0.1.39
Requires-Dist: steer-materials==0.1.24
Requires-Dist: steer-opencell-data==0.0.14
Requires-Dist: shapely==2.1.1
Dynamic: license-file
